python_hll2/__init__.py
python_hll2/hll.py
python_hll2/hlltype.py
python_hll2/hllutil.py
python_hll2/serialization.py
python_hll2/util.py
python_hll2-2.0.2.dist-info/licenses/LICENSE
python_hll2-2.0.2.dist-info/WHEEL
python_hll2-2.0.2.dist-info/METADATA
python_hll2-2.0.2.dist-info/RECORD
