Metadata-Version: 2.4
Name: python-hll2
Version: 2.0.2
Summary: A Python implementation of HyperLogLog. Maintained fork from python-hll
Author-email: Jon Aquino <jonathan.aquino@adroll.com>, Kushagra Verma <kushagra.verma@adroll.com>, Alex Leu <alex.leu@adroll.com>, Michael Tran <michael.tran@adroll.com>, Rodrigo Westrupp <rodrigo.westrupp@adroll.com>, Sridharan Subramanian <sridharan.subramanian@adroll.com>, Piyush Srivastava <piyush.srivastava@adroll.com>
Maintainer-email: Jonathan Schaeffer <jonathan.schaeffer@univ-grenoble-alpes.fr>
Requires-Python: >=3.11
License-Expression: MIT
License-File: LICENSE
Requires-Dist: numpy>=2.3.5
